CryptoPayAPI/__init__.py
CryptoPayAPI/AioCryptoPay/__init__.py
CryptoPayAPI/AioCryptoPay/cryptopay.py
CryptoPayAPI/CryptoPay/__init__.py
CryptoPayAPI/CryptoPay/cryptopay.py
CryptoPayAPI/exceptions/__init__.py
CryptoPayAPI/exceptions/exceptions.py
CryptoPayAPI/types/__init__.py
CryptoPayAPI/types/app/__init__.py
CryptoPayAPI/types/app/app.py
CryptoPayAPI/types/app_stats/__init__.py
CryptoPayAPI/types/app_stats/app_stats.py
CryptoPayAPI/types/asset/__init__.py
CryptoPayAPI/types/asset/asset.py
CryptoPayAPI/types/asset/base.py
CryptoPayAPI/types/balance/__init__.py
CryptoPayAPI/types/balance/balance.py
CryptoPayAPI/types/base/__init__.py
CryptoPayAPI/types/base/base.py
CryptoPayAPI/types/check/__init__.py
CryptoPayAPI/types/check/check.py
CryptoPayAPI/types/cryptopay/__init__.py
CryptoPayAPI/types/cryptopay/cryptopay.py
CryptoPayAPI/types/currency/__init__.py
CryptoPayAPI/types/currency/currency.py
CryptoPayAPI/types/currency_type/__init__.py
CryptoPayAPI/types/currency_type/base.py
CryptoPayAPI/types/currency_type/currency_type.py
CryptoPayAPI/types/exchange_rate/__init__.py
CryptoPayAPI/types/exchange_rate/exchange_rate.py
CryptoPayAPI/types/fiat/__init__.py
CryptoPayAPI/types/fiat/base.py
CryptoPayAPI/types/fiat/fiat.py
CryptoPayAPI/types/invoice/__init__.py
CryptoPayAPI/types/invoice/invoice.py
CryptoPayAPI/types/transfer/__init__.py
CryptoPayAPI/types/transfer/transfer.py
CryptoPayAPI-1.4.8.dist-info/LICENSE
CryptoPayAPI-1.4.8.dist-info/METADATA
CryptoPayAPI-1.4.8.dist-info/WHEEL
CryptoPayAPI-1.4.8.dist-info/top_level.txt
CryptoPayAPI-1.4.8.dist-info/RECORD
