Metadata-Version: 2.1
Name: CryptoPayAPI
Version: 1.4.8
Summary: Simple library for https://t.me/CryptoBot
Home-page: https://github.com/aweone/CryptoPayAPI
Author: aweone
Author-email: aweonegithub@gmail.com
License: MIT License
Project-URL: Source Code, https://github.com/aweone/CryptoPayAPI
Project-URL: API Docs, https://help.crypt.bot/crypto-pay-api
Keywords: crypto api pay p2p wrapper async cryptopay cryptopayapi
License-File: LICENSE
Requires-Dist: aiohttp ~=3.8.1
Requires-Dist: httpx ~=0.23.0
